sdbdump/__init__.py
sdbdump/main.py
sdbdump/sdb_helper.py
sdbdump-0.1.2.data/scripts/sdbdump
sdbdump-0.1.2.dist-info/DESCRIPTION.rst
sdbdump-0.1.2.dist-info/METADATA
sdbdump-0.1.2.dist-info/RECORD
sdbdump-0.1.2.dist-info/WHEEL
sdbdump-0.1.2.dist-info/metadata.json
sdbdump-0.1.2.dist-info/top_level.txt
