Metadata-Version: 2.0
Name: sdbdump
Version: 0.1.2
Summary: Import/export AWS SimpleDB databases from/to JSON files.
Home-page: https://github.com/Maerig/sdbdump
Author: Jean-Loup Roussel-Clouet
Author-email: maerig@gmail.com
License: MIT
Platform: UNKNOWN
Requires-Python: >=3.6.*
Requires-Dist: boto3 (==1.6.14)
